oups/__init__.py
oups/date_utils.py
oups/defines.py
oups/numpy_utils.py
oups/stateful_loop/__init__.py
oups/stateful_loop/loop_persistence_io.py
oups/stateful_loop/stateful_loop.py
oups/stateful_loop/validate_loop_usage.py
oups/stateful_ops/__init__.py
oups/stateful_ops/aggstream/__init__.py
oups/stateful_ops/aggstream/aggstream.py
oups/stateful_ops/aggstream/cumsegagg.py
oups/stateful_ops/aggstream/jcumsegagg.py
oups/stateful_ops/aggstream/segmentby.py
oups/stateful_ops/aggstream/utils.py
oups/stateful_ops/asof_merger/__init__.py
oups/stateful_ops/asof_merger/asof_merger.py
oups/stateful_ops/asof_merger/get_config.py
oups/stateful_ops/asof_merger/validate_params.py
oups/store/__init__.py
oups/store/filepath_utils.py
oups/store/indexer.py
oups/store/ordered_parquet_dataset/__init__.py
oups/store/ordered_parquet_dataset/metadata_filename.py
oups/store/ordered_parquet_dataset/ordered_parquet_dataset/__init__.py
oups/store/ordered_parquet_dataset/ordered_parquet_dataset/base.py
oups/store/ordered_parquet_dataset/ordered_parquet_dataset/read_only.py
oups/store/ordered_parquet_dataset/parquet_adapter.py
oups/store/ordered_parquet_dataset/write/__init__.py
oups/store/ordered_parquet_dataset/write/iter_merge_split_data.py
oups/store/ordered_parquet_dataset/write/merge_split_strategies/__init__.py
oups/store/ordered_parquet_dataset/write/merge_split_strategies/base.py
oups/store/ordered_parquet_dataset/write/merge_split_strategies/n_rows_strategy.py
oups/store/ordered_parquet_dataset/write/merge_split_strategies/time_period_strategy.py
oups/store/ordered_parquet_dataset/write/write.py
oups/store/store/__init__.py
oups/store/store/dataset_cache.py
oups/store/store/iter_intersections.py
oups/store/store/store.py
oups-2025.11.3.dist-info/METADATA
oups-2025.11.3.dist-info/WHEEL
oups-2025.11.3.dist-info/licenses/LICENSE
oups-2025.11.3.dist-info/RECORD
