Metadata-Version: 2.4
Name: oups
Version: 2025.11.3
Summary: Out-of-core pipelines over ordered data: StatefulLoop, stateful ops, and ordered Parquet Store.
License: Apache-2.0
License-File: LICENSE
Keywords: out-of-core,streaming,stateful,time-series,pandas,parquet,data-engineering
Author: pierrot
Requires-Python: >=3.13,<4.0
Classifier: License :: OSI Approved :: Apache Software License
Classifier: Programming Language :: Python :: 3
Classifier: Programming Language :: Python :: 3.13
Classifier: Programming Language :: Python :: 3.14
Requires-Dist: cloudpickle (>=3.1.1)
Requires-Dist: fastparquet (>=2023.10.1)
Requires-Dist: flufl-lock (>=8.2.0)
Requires-Dist: joblib (>=1.3.2)
Requires-Dist: numba (>=0.61.2)
Requires-Dist: numpy (>=2.0)
Requires-Dist: pandas (>=2.2.3)
Requires-Dist: sortedcontainers (>=2.4.0)
Project-URL: Changelog, https://codeberg.org/pierrot/oups/src/branch/main/CHANGELOG.md
Project-URL: Documentation, https://pierrot.codeberg.page/oups
Project-URL: Homepage, https://codeberg.org/pierrot/oups
Project-URL: Issues, https://codeberg.org/pierrot/oups/issues
Project-URL: Source, https://codeberg.org/pierrot/oups
